padded_sel/run_wrapper.py
padded_sel/selenium_wrapper.py
padded_sel-1.2.1.dist-info/DESCRIPTION.rst
padded_sel-1.2.1.dist-info/METADATA
padded_sel-1.2.1.dist-info/RECORD
padded_sel-1.2.1.dist-info/WHEEL
padded_sel-1.2.1.dist-info/metadata.json
padded_sel-1.2.1.dist-info/top_level.txt
