Metadata-Version: 2.0
Name: padded-sel
Version: 1.2.1
Summary: Selenium Webdriver wrapper to make it easy to interact with page elements and handle failures in the way you want to.
Home-page: https://github.com/g-farrow/padded_sel
Author: Greg Farrow
Author-email: greg.farrow1@gmail.com
License: MIT
Keywords: selenium wrapper helper automated testing framework
Platform: UNKNOWN
Classifier: Programming Language :: Python :: 3
Classifier: Programming Language :: Python :: 3.2
Classifier: Programming Language :: Python :: 3.3
Classifier: Programming Language :: Python :: 3.4
Classifier: Programming Language :: Python :: 3.5
Requires-Python: >=3
Requires-Dist: selenium
